escape_windows_filepath/LICENSE
escape_windows_filepath/README.MD
escape_windows_filepath/__init__.py
escape_windows_filepath/requirements.txt
escape_windows_filepath/thirdparty.json
escape_windows_filepath-0.10.dist-info/LICENSE.rst
escape_windows_filepath-0.10.dist-info/METADATA
escape_windows_filepath-0.10.dist-info/WHEEL
escape_windows_filepath-0.10.dist-info/top_level.txt
escape_windows_filepath-0.10.dist-info/RECORD
