Metadata-Version: 2.1
Name: escape-windows-filepath
Version: 0.10
Summary: Escaping file paths (Windows) without crying and losing one's mind
Home-page: https://github.com/hansalemaos/escape_windows_filepath
Author: Johannes Fischer
Author-email: <aulasparticularesdealemaosp@gmail.com>
License: MIT
Keywords: path,pathlib,escaping,os,window,file,folder
Classifier: Development Status :: 4 - Beta
Classifier: Programming Language :: Python :: 3 :: Only
Classifier: Programming Language :: Python :: 3.10
Classifier: Topic :: Scientific/Engineering :: Visualization
Classifier: Topic :: Software Development :: Libraries :: Python Modules
Classifier: Topic :: Utilities
License-File: LICENSE.rst
